fascia_dem/Functions.py
fascia_dem/Input.py
fascia_dem/Layer.py
fascia_dem/Sample.py
fascia_dem/__init__.py
fascia_dem-0.0.1.dist-info/licenses/LICENSE
fascia_dem-0.0.1.dist-info/METADATA
fascia_dem-0.0.1.dist-info/WHEEL
fascia_dem-0.0.1.dist-info/top_level.txt
fascia_dem-0.0.1.dist-info/RECORD
