Metadata-Version: 2.4
Name: fascia_dem
Version: 0.0.1
Summary: A package allowing to create my fascia domaina nd to run the discrete element model simulation.
Author-email: Lagache Alexandre <alexandre.lagache@ensam.eu>
License-Expression: MIT
Classifier: Programming Language :: Python :: 3
Classifier: Operating System :: OS Independent
Requires-Python: >=3.9
License-File: LICENSE
Dynamic: license-file
